profiler/__init__.py
profiler/__main__.py
profiler/datamodel.py
imc_prosperity_profiler-0.0.5.dist-info/METADATA
imc_prosperity_profiler-0.0.5.dist-info/WHEEL
imc_prosperity_profiler-0.0.5.dist-info/entry_points.txt
imc_prosperity_profiler-0.0.5.dist-info/top_level.txt
imc_prosperity_profiler-0.0.5.dist-info/RECORD
