Metadata-Version: 2.4
Name: IMC_Prosperity-profiler
Version: 0.0.5
Summary: A program to visualize prosperity run method performance
Author-email: r4v4rg4s <ravargas.42t@gmail.com>
License-Expression: MIT
Project-URL: Homepage, https://github.com/rvargas42/IMC_Prosperity-profiler
Project-URL: Issues, https://github.com/rvargas42/IMC_Prosperity-profiler/issues
Classifier: Programming Language :: Python :: 3
Classifier: Operating System :: OS Independent
Requires-Python: >=3.8
Requires-Dist: jsonpickle>=4.0.2
Requires-Dist: numpy>=1.24.4
Requires-Dist: pandas>=2.0.3
Requires-Dist: snakeviz>=2.2.1
